twclassify/__init__.py
twclassify/twclassify.py
twclassify-0.1.3.dist-info/DESCRIPTION.rst
twclassify-0.1.3.dist-info/METADATA
twclassify-0.1.3.dist-info/RECORD
twclassify-0.1.3.dist-info/WHEEL
twclassify-0.1.3.dist-info/metadata.json
twclassify-0.1.3.dist-info/top_level.txt
