Metadata-Version: 2.0
Name: twclassify
Version: 0.1.3
Summary: .
Home-page: https://github.com/aronwc/twclassify
Author: Aron Culotta
Author-email: aronwc@gmail.com
License: MIT license
Keywords: twclassify
Platform: UNKNOWN
Classifier: Development Status :: 2 - Pre-Alpha
Classifier: Intended Audience :: Developers
Classifier: License :: OSI Approved :: MIT License
Classifier: Natural Language :: English
Classifier: Programming Language :: Python :: 2
Classifier: Programming Language :: Python :: 2.6
Classifier: Programming Language :: Python :: 2.7
Classifier: Programming Language :: Python :: 3
Classifier: Programming Language :: Python :: 3.3
Classifier: Programming Language :: Python :: 3.4
Classifier: Programming Language :: Python :: 3.5
